{
  "$schema": "https://raw.githubusercontent.com/tauri-apps/tauri/dev/crates/tauri-cli/schema.json",
  "productName": "PDF Seeker",
  "version": "0.1.0",
  "identifier": "com.pdfseeker.app",
  "build": {
    "beforeDevCommand": "npm run dev",
    "devUrl": "http://localhost:1420",
    "beforeBuildCommand": "npm run build",
    "frontendDist": "../dist"
  },
  "app": {
    "windows": [
      {
        "title": "PDF Seeker",
        "width": 1280,
        "height": 800,
        "minWidth": 900,
        "minHeight": 600,
        "center": true,
        "decorations": true
      }
    ],
    "security": {
      "csp": null
    }
  },
  "bundle": {
    "active": true,
    "targets": "all"
  }
}
